{
  "requested_address": "4400 W WEDGE DR, FAYETTEVILLE, AR 72704-7516",
  "property_record": {
    "address": "4400 W WEDGE DR",
    "mail_address": "4400 W WEDGE DR, FAYETTEVILLE, AR 72704-7516",
    "owner": "PARDUE, MICHEL & KAREN",
    "subdivision": "CROSS KEYS S/D PH I",
    "city": "Fayetteville",
    "assessed_value": "78,042",
    "str_location": "12-16-31",
    "block_lot": "N/A / 051",
    "acres": "N/A",
    "legal": ""
  },
  "type": "FeatureCollection",
  "features": [
    {
      "type": "Feature",
      "properties": {
        "datasource": {
          "sourcename": "openstreetmap",
          "attribution": "\u00a9 OpenStreetMap contributors",
          "license": "Open Database License",
          "url": "https://www.openstreetmap.org/copyright"
        },
        "country": "United States",
        "country_code": "us",
        "state": "Arkansas",
        "county": "Washington County",
        "city": "Fayetteville",
        "postcode": "72704",
        "street": "West Wedge Drive",
        "housenumber": "4400",
        "lon": -94.22355820512388,
        "lat": 36.072360149999994,
        "state_code": "AR",
        "result_type": "building",
        "formatted": "4400 West Wedge Drive, Fayetteville, AR 72704, United States of America",
        "address_line1": "4400 West Wedge Drive",
        "address_line2": "Fayetteville, AR 72704, United States of America",
        "category": "building.residential",
        "timezone": {
          "name": "America/Chicago",
          "offset_STD": "-06:00",
          "offset_STD_seconds": -21600,
          "offset_DST": "-05:00",
          "offset_DST_seconds": -18000,
          "abbreviation_STD": "CST",
          "abbreviation_DST": "CDT"
        },
        "plus_code": "86873QCG+WH",
        "plus_code_short": "3QCG+WH, 72704 Fayetteville, United States",
        "rank": {
          "importance": 0.41000999999999993,
          "popularity": 2.0004326223553828,
          "confidence": 1.0,
          "confidence_city_level": 1.0,
          "confidence_street_level": 1.0,
          "confidence_building_level": 1.0,
          "match_type": "full_match"
        },
        "place_id": "519cf012c74e8e57c0594ee4ee1843094240f00102f9014f37681d00000000c00203"
      },
      "geometry": {
        "type": "Point",
        "coordinates": [
          -94.22355820512388,
          36.072360149999994
        ]
      },
      "bbox": [
        -94.223677,
        36.0722235,
        -94.223441,
        36.0724372
      ]
    }
  ],
  "query": {
    "text": "4400 W WEDGE DR, FAYETTEVILLE, AR 72704-7516",
    "parsed": {
      "housenumber": "4400",
      "street": "w wedge dr",
      "postcode": "72704-7516",
      "city": "fayetteville",
      "state": "ar",
      "expected_type": "building"
    }
  }
}